pennylane_pq/__init__.py
pennylane_pq/_version.py
pennylane_pq/devices.py
pennylane_pq/expval.py
pennylane_pq/ops.py
pennylane_pq/pqops.py
PennyLane_PQ-0.34.0.dist-info/LICENSE
PennyLane_PQ-0.34.0.dist-info/METADATA
PennyLane_PQ-0.34.0.dist-info/WHEEL
PennyLane_PQ-0.34.0.dist-info/entry_points.txt
PennyLane_PQ-0.34.0.dist-info/top_level.txt
PennyLane_PQ-0.34.0.dist-info/RECORD
